odoo8_addon_contract_journal-8.0.1.0.0.99.dev17-py2.7-nspkg.pth
odoo8_addon_contract_journal-8.0.1.0.0.99.dev17.dist-info/METADATA
odoo8_addon_contract_journal-8.0.1.0.0.99.dev17.dist-info/RECORD
odoo8_addon_contract_journal-8.0.1.0.0.99.dev17.dist-info/WHEEL
odoo8_addon_contract_journal-8.0.1.0.0.99.dev17.dist-info/namespace_packages.txt
odoo8_addon_contract_journal-8.0.1.0.0.99.dev17.dist-info/top_level.txt
odoo_addons/contract_journal/README.rst
odoo_addons/contract_journal/__init__.py
odoo_addons/contract_journal/__openerp__.py
odoo_addons/contract_journal/i18n/ar.po
odoo_addons/contract_journal/i18n/bs.po
odoo_addons/contract_journal/i18n/ca.po
odoo_addons/contract_journal/i18n/ca_ES.po
odoo_addons/contract_journal/i18n/contract_journal.pot
odoo_addons/contract_journal/i18n/cs.po
odoo_addons/contract_journal/i18n/da.po
odoo_addons/contract_journal/i18n/de.po
odoo_addons/contract_journal/i18n/el_GR.po
odoo_addons/contract_journal/i18n/en_GB.po
odoo_addons/contract_journal/i18n/es.po
odoo_addons/contract_journal/i18n/es_CR.po
odoo_addons/contract_journal/i18n/es_EC.po
odoo_addons/contract_journal/i18n/es_ES.po
odoo_addons/contract_journal/i18n/es_MX.po
odoo_addons/contract_journal/i18n/es_VE.po
odoo_addons/contract_journal/i18n/et.po
odoo_addons/contract_journal/i18n/fi.po
odoo_addons/contract_journal/i18n/fr.po
odoo_addons/contract_journal/i18n/gl.po
odoo_addons/contract_journal/i18n/hr.po
odoo_addons/contract_journal/i18n/hr_HR.po
odoo_addons/contract_journal/i18n/hu.po
odoo_addons/contract_journal/i18n/id.po
odoo_addons/contract_journal/i18n/it.po
odoo_addons/contract_journal/i18n/ja.po
odoo_addons/contract_journal/i18n/lt.po
odoo_addons/contract_journal/i18n/lt_LT.po
odoo_addons/contract_journal/i18n/mk.po
odoo_addons/contract_journal/i18n/mn.po
odoo_addons/contract_journal/i18n/nb.po
odoo_addons/contract_journal/i18n/nb_NO.po
odoo_addons/contract_journal/i18n/nl.po
odoo_addons/contract_journal/i18n/nl_BE.po
odoo_addons/contract_journal/i18n/pl.po
odoo_addons/contract_journal/i18n/pt.po
odoo_addons/contract_journal/i18n/pt_BR.po
odoo_addons/contract_journal/i18n/pt_PT.po
odoo_addons/contract_journal/i18n/ro.po
odoo_addons/contract_journal/i18n/ro_RO.po
odoo_addons/contract_journal/i18n/ru.po
odoo_addons/contract_journal/i18n/sk_SK.po
